GaPFlow/db.py
GaPFlow/topography.py
GaPFlow/io.py
GaPFlow/__init__.py
GaPFlow/integrate.py
GaPFlow/problem.py
GaPFlow/utils.py
GaPFlow/info.py
GaPFlow/__main__.py
GaPFlow/_vendor/lammps/LICENSE
GaPFlow/_vendor/lammps/constants.py
GaPFlow/_vendor/lammps/numpy_wrapper.py
GaPFlow/_vendor/lammps/__init__.py
GaPFlow/_vendor/lammps/core.py
GaPFlow/_vendor/lammps/formats.py
GaPFlow/_vendor/lammps/liblammps_mpi.dylib
GaPFlow/_vendor/lammps/data.py
GaPFlow/_vendor/lammps/liblammps_mpi.0.dylib
GaPFlow/models/sound.py
GaPFlow/models/bwr_coeffs.txt
GaPFlow/models/pressure.py
GaPFlow/models/gp.py
GaPFlow/models/viscous.py
GaPFlow/models/__init__.py
GaPFlow/models/stress.py
GaPFlow/models/viscosity.py
GaPFlow/models/profiles.py
GaPFlow/cli/animate2d.py
GaPFlow/cli/plot_history.py
GaPFlow/cli/animate1d.py
GaPFlow/cli/plot_height.py
GaPFlow/cli/plot_frames.py
GaPFlow/cli/plot_frame.py
GaPFlow/.dylibs/libpng16.16.dylib
GaPFlow/.dylibs/libjpeg.8.3.2.dylib
GaPFlow/viz/animations.py
GaPFlow/viz/gapflow.mplstyle
GaPFlow/viz/plotting.py
GaPFlow/viz/__init__.py
GaPFlow/viz/utils.py
GaPFlow/md/readme_template.yml
GaPFlow/md/_lammps.py
GaPFlow/md/runner.py
GaPFlow/md/__init__.py
GaPFlow/md/utils.py
GaPFlow/md/moltemplate.py
gapflow-1.0.2rc1.dist-info/RECORD
gapflow-1.0.2rc1.dist-info/WHEEL
gapflow-1.0.2rc1.dist-info/entry_points.txt
gapflow-1.0.2rc1.dist-info/METADATA
gapflow-1.0.2rc1.dist-info/licenses/COPYING
gapflow-1.0.2rc1.dist-info/licenses/GaPFlow/_vendor/lammps/LICENSE
gapflow-1.0.2rc1.dist-info/licenses/LICENSES/GPL-2.0.txt
gapflow-1.0.2rc1.dist-info/licenses/LICENSES/MIT.txt
gapflow-1.0.2rc1.dist-info/licenses/lammps/LICENSE
