Metadata-Version: 2.4
Name: GaPFlow
Version: 1.0.2rc1
Summary: Gap-averaged flow simulations with Gaussian process regression.
Author-Email: Hannes Holey <hannes.holey@unimi.it>, Christoph Huber <christop.huber@kit.edu>
License-Expression: GPL-2.0
License-File: COPYING
License-File: GaPFlow/_vendor/lammps/LICENSE
License-File: LICENSES/GPL-2.0.txt
License-File: LICENSES/MIT.txt
License-File: lammps/LICENSE
Classifier: Programming Language :: Python :: 3
Project-URL: Source, https://github.com/hannes-holey/gapflow
Requires-Python: >=3.10
Requires-Dist: muGrid>=0.105.0
Requires-Dist: tinygp>=0.3.0
Requires-Dist: jax
Requires-Dist: numpy
Requires-Dist: scipy
Requires-Dist: jaxopt==0.8.5
Requires-Dist: netCDF4>=1.7.2
Requires-Dist: dtoolcore>=3.19.0
Requires-Dist: dtool-lookup-api>=0.10.2
Requires-Dist: matplotlib
Requires-Dist: polars
Requires-Dist: ruamel.yaml
Requires-Dist: ase
Requires-Dist: moltemplate
Requires-Dist: ContactMechanics>=1.8.0
Requires-Dist: IPython
Provides-Extra: parallel
Requires-Dist: mpi4py; extra == "parallel"
Provides-Extra: test
Requires-Dist: pytest; extra == "test"
Requires-Dist: pytest-cov; extra == "test"
Provides-Extra: doc
Requires-Dist: sphinx; extra == "doc"
Requires-Dist: sphinx_book_theme; extra == "doc"
Requires-Dist: myst-nb; extra == "doc"
Requires-Dist: jupytext; extra == "doc"
Requires-Dist: sympy; extra == "doc"
